stormai/__init__.py
stormai/core.py
stormai-0.1.0.dist-info/licenses/LICENSE
stormai-0.1.0.dist-info/METADATA
stormai-0.1.0.dist-info/WHEEL
stormai-0.1.0.dist-info/top_level.txt
stormai-0.1.0.dist-info/RECORD
